{
  "links": [
    {
      "id": "a787",
      "code": "gYsWj9",
      "url": "https://google.com",
      "createat": "2025-11-26T00:23:41.095Z",
      "usercreate": "anonymous"
    },
    {
      "id": "1f4c",
      "code": "hTzX1D",
      "url": "https://facebook.com",
      "createat": "2025-11-26T00:25:01.486Z",
      "usercreate": "anonymous"
    },
    {
      "id": "3b2e",
      "code": "Jv8KpL",
      "url": "https://twitter.com",
      "createat": "2025-11-26T00:26:15.123Z",
      "usercreate": "anonymous"
    },
    {
      "id": "4c5d",
      "code": "LmNqR2",
      "url": "https://linkedin.com",
      "createat": "2025-11-26T00:27:30.456Z",
      "usercreate": "anonymous"
    },
    {
      "id": "5e6f",
      "code": "NpQrS3",
      "url": "https://instagram.com",
      "createat": "2025-11-26T00:28:45.789Z",
      "usercreate": "anonymous"
    },
    {
      "id": "72aa",
      "code": "CFPQgd",
      "url": "https://github.com",
      "createat": "2025-11-26T00:29:27.407Z",
      "usercreate": "anonymous"
    },
    {
      "id": "89a9",
      "code": "CqmOBS",
      "url": "https://vite.com",
      "createat": "2025-11-26T00:30:37.025Z",
      "usercreate": "anonymous"
    }
  ]
}